<?xml version="1.0" encoding="UTF-8"?>
<!DOCTYPE mapper PUBLIC "-//mybatis.org//DTD Mapper 3.0//EN" "http://mybatis.org/dtd/mybatis-3-mapper.dtd">
<mapper namespace="com.dao.OrderDetailMapper">
  <resultMap id="BaseResultMap" type="com.bean.OrderDetail">
    <!--
      WARNING - @mbg.generated
      This element is automatically generated by MyBatis Generator, do not modify.
    -->
    <id column="detail_id" jdbcType="INTEGER" property="detailId" />
    <result column="detail_order" jdbcType="VARCHAR" property="detailOrder" />
    <result column="detail_goods" jdbcType="INTEGER" property="detailGoods" />
    <result column="detail_price" jdbcType="REAL" property="detailPrice" />
    <result column="detail_num" jdbcType="INTEGER" property="detailNum" />
  </resultMap>
  <delete id="deleteByPrimaryKey" parameterType="java.lang.Integer">
    <!--
      WARNING - @mbg.generated
      This element is automatically generated by MyBatis Generator, do not modify.
    -->
    delete from order_detail
    where detail_id = #{detailId,jdbcType=INTEGER}
  </delete>
  <insert id="insert" parameterType="com.bean.OrderDetail">
    <!--
      WARNING - @mbg.generated
      This element is automatically generated by MyBatis Generator, do not modify.
    -->
    insert into order_detail (detail_id, detail_order, detail_goods, 
      detail_price, detail_num)
    values (#{detailId,jdbcType=INTEGER}, #{detailOrder,jdbcType=VARCHAR}, #{detailGoods,jdbcType=INTEGER}, 
      #{detailPrice,jdbcType=REAL}, #{detailNum,jdbcType=INTEGER})
  </insert>
  <update id="updateByPrimaryKey" parameterType="com.bean.OrderDetail">
    <!--
      WARNING - @mbg.generated
      This element is automatically generated by MyBatis Generator, do not modify.
    -->
    update order_detail
    set detail_order = #{detailOrder,jdbcType=VARCHAR},
      detail_goods = #{detailGoods,jdbcType=INTEGER},
      detail_price = #{detailPrice,jdbcType=REAL},
      detail_num = #{detailNum,jdbcType=INTEGER}
    where detail_id = #{detailId,jdbcType=INTEGER}
  </update>
  <select id="selectByPrimaryKey" parameterType="java.lang.Integer" resultMap="BaseResultMap">
    <!--
      WARNING - @mbg.generated
      This element is automatically generated by MyBatis Generator, do not modify.
    -->
    select detail_id, detail_order, detail_goods, detail_price, detail_num
    from order_detail
    where detail_id = #{detailId,jdbcType=INTEGER}
  </select>
  <select id="selectAll" resultMap="BaseResultMap">
    <!--
      WARNING - @mbg.generated
      This element is automatically generated by MyBatis Generator, do not modify.
    -->
    select detail_id, detail_order, detail_goods, detail_price, detail_num
    from order_detail
  </select>

  <select id="selectdetailId" resultMap="BaseResultMap" parameterType="String" >
    select detail_id
    from order_detail
    where detail_order = #{detailOrder,jdbcType=VARCHAR}
  </select>


</mapper>